HISTORY.md
MANIFEST.in
README.md
requirements.txt
setup.cfg
setup.py
tests/__init__.py
tests/test_channel_info_extractor.py
tests/test_cli.py
yt_archive/__init__.py
yt_archive/cli.py
yt_archive/extractor.py
yt_channels_archive.egg-info/PKG-INFO
yt_channels_archive.egg-info/SOURCES.txt
yt_channels_archive.egg-info/dependency_links.txt
yt_channels_archive.egg-info/entry_points.txt
yt_channels_archive.egg-info/not-zip-safe
yt_channels_archive.egg-info/requires.txt
yt_channels_archive.egg-info/top_level.txt