Metadata-Version: 2.1
Name: yt-channels-archive
Version: 0.2.2
Summary: A CLI tool to backup multiple YouTube channels along with their associated metadata and thumbnails. In the highest available quality.
Home-page: https://github.com/project-49476/yt-channels-archive
Author: O'Dwyer Software
Author-email: hello@odwyer.software
License: Apache 2.0
Platform: UNKNOWN
Classifier: Intended Audience :: Developers
Classifier: Operating System :: OS Independent
Classifier: Programming Language :: Python
Classifier: Programming Language :: Python :: 3
Classifier: Topic :: Internet :: WWW/HTTP
